woo_db_agent-0.1.1.dist-info/licenses/LICENSE
woo_db_agent-0.1.1.dist-info/licenses/license_file.txt
woodbagent/__init__.py
woodbagent/cli.py
woodbagent/config.py
woodbagent/core.py
woodbagent/executor.py
woo_db_agent-0.1.1.dist-info/METADATA
woo_db_agent-0.1.1.dist-info/WHEEL
woo_db_agent-0.1.1.dist-info/top_level.txt
woo_db_agent-0.1.1.dist-info/RECORD
