Metadata-Version: 2.4
Name: woo-db-agent
Version: 0.1.1
License-File: LICENSE
License-File: license_file.txt
Dynamic: description
Dynamic: description-content-type
Dynamic: license-file
